data_checks/__init__.py
data_checks/__main__.py
data_checks/init.py
data_checks/base/__init__.py
data_checks/base/check.py
data_checks/base/check_types.py
data_checks/base/suite.py
data_checks/base/suite_helper_types.py
data_checks/base/suite_types.py
data_checks/base/actions/__init__.py
data_checks/base/actions/action_types.py
data_checks/base/actions/execution_context.py
data_checks/base/actions/check/__init__.py
data_checks/base/actions/check/check_action.py
data_checks/base/actions/check/error_logging_check_action.py
data_checks/base/actions/check/execution_database_action.py
data_checks/base/actions/check/main_database_action.py
data_checks/base/actions/check/rule_alerting_action.py
data_checks/base/actions/check/skip_rule_execution_action.py
data_checks/base/actions/suite/__init__.py
data_checks/base/actions/suite/error_logging_suite_action.py
data_checks/base/actions/suite/find_suite_model_action.py
data_checks/base/actions/suite/main_database_action.py
data_checks/base/actions/suite/setup_check_actions_action.py
data_checks/base/actions/suite/suite_action.py
data_checks/base/actions/suite/update_check_from_internals_action.py
data_checks/base/exceptions/__init__.py
data_checks/base/exceptions/data_check_exception.py
data_checks/base/exceptions/skip_execution_exception.py
data_checks/base/mixins/action_mixin.py
data_checks/classes/data_check.py
data_checks/classes/data_suite.py
data_checks/classes/group_data_suite.py
data_checks/conf/__init__.py
data_checks/conf/data_check_registry.py
data_checks/conf/data_suite_registry.py
data_checks/conf/global_settings.py
data_checks/conf/settings.py
data_checks/database/__init__.py
data_checks/database/managers/__init__.py
data_checks/database/managers/base_manager.py
data_checks/database/managers/check_manager.py
data_checks/database/managers/rule_execution_manager.py
data_checks/database/managers/rule_manager.py
data_checks/database/managers/suite_manager.py
data_checks/database/managers/models/__init__.py
pydata_checks-0.0.83.dist-info/LICENSE
pydata_checks-0.0.83.dist-info/METADATA
pydata_checks-0.0.83.dist-info/WHEEL
pydata_checks-0.0.83.dist-info/top_level.txt
pydata_checks-0.0.83.dist-info/RECORD
