Metadata-Version: 2.1
Name: pydata-checks
Version: 0.0.83
Summary: Data quality checks that don't suck.
Author-email: Ivan Zhang <ivanzhangofficial@gmail.com>
License: MIT License
Project-URL: Homepage, https://github.com/SuperiorityComplex/data-checks
Project-URL: Bug Tracker, https://github.com/SuperiorityComplex/data-checks/issues
Requires-Python: >=3.7
License-File: LICENSE
Requires-Dist: APScheduler
Requires-Dist: certifi
Requires-Dist: charset-normalizer
Requires-Dist: idna
Requires-Dist: pytz
Requires-Dist: requests
Requires-Dist: six
Requires-Dist: SQLAlchemy
Requires-Dist: typing-extensions
Requires-Dist: tzlocal
Requires-Dist: urllib3
Requires-Dist: numpy
Requires-Dist: pandas
Requires-Dist: python-dateutil
